sneakersync/__init__.py
sneakersync/exception.py
sneakersync/main.py
sneakersync/operations.py
sneakersync/rsync.py
sneakersync/state.py
sneakersync-1.2.2.dist-info/LICENSE.txt
sneakersync-1.2.2.dist-info/METADATA
sneakersync-1.2.2.dist-info/WHEEL
sneakersync-1.2.2.dist-info/entry_points.txt
sneakersync-1.2.2.dist-info/top_level.txt
sneakersync-1.2.2.dist-info/RECORD
