Metadata-Version: 2.1
Name: sneakersync
Version: 1.2.2
Summary: Synchronize files through the sneakernet
Home-page: https://github.com/lamyj/sneakersync
Author: Julien Lamy
Author-email: julien@seasofcheese.net
License: MIT
Keywords: synchronization,removable drive,sneakernet,rsync
Platform: UNKNOWN
Classifier: Development Status :: 5 - Production/Stable
Classifier: Environment :: Console
Classifier: Intended Audience :: End Users/Desktop
Classifier: Intended Audience :: Information Technology
Classifier: Intended Audience :: System Administrators
Classifier: Topic :: Communications :: File Sharing
Classifier: Topic :: System :: Archiving :: Mirroring
Classifier: License :: OSI Approved :: MIT License
Classifier: Programming Language :: Python :: 3
Requires-Dist: pyyaml
